politely/__init__.py
politely/errors.py
politely/fetchers.py
politely/modeling_gpt2_scorer.py
politely/modeling_heuristic_scorer.py
politely/modeling_sbg_scorer.py
politely/modeling_scorer.py
politely/rules.py
politely/styler.py
politely-4.1.0.dist-info/METADATA
politely-4.1.0.dist-info/WHEEL
politely-4.1.0.dist-info/RECORD
