Metadata-Version: 2.1
Name: politely
Version: 4.1.0
Summary: An explainable styler for the Korean language
Author: Eu-Bin KIM
Author-email: tlrndk123@gmail.com
Requires-Python: >=3.9.12,<4.0.0
Classifier: Programming Language :: Python :: 3
Classifier: Programming Language :: Python :: 3.10
Classifier: Programming Language :: Python :: 3.11
Classifier: Programming Language :: Python :: 3.12
Provides-Extra: gpt2
Requires-Dist: kiwipiepy (>=0.17.0,<0.18.0)
Requires-Dist: torch (>=2.2.2,<3.0.0) ; extra == "gpt2"
Requires-Dist: transformers (>=4.39.3,<5.0.0) ; extra == "gpt2"
